MANIFEST.in
Makefile
README
fmspy.cfg
setup.py
examples/chat/.gitignore
examples/chat/Chat.hx
examples/chat/Makefile
examples/chat/app.hxml
examples/chat/chat.swf
examples/chat/index.html
examples/echotest/echo_test.swf
examples/echotest/index.html
fmspy/__init__.py
fmspy/_time.py
fmspy/config.py
fmspy.egg-info/PKG-INFO
fmspy.egg-info/SOURCES.txt
fmspy.egg-info/dependency_links.txt
fmspy.egg-info/not-zip-safe
fmspy.egg-info/requires.txt
fmspy.egg-info/top_level.txt
fmspy/application/__init__.py
fmspy/application/application.py
fmspy/application/factory.py
fmspy/application/interfaces.py
fmspy/application/room.py
fmspy/application/tests/__init__.py
fmspy/application/tests/plugin_test_application.py
fmspy/application/tests/test_application.py
fmspy/application/tests/test_factory.py
fmspy/application/tests/test_room.py
fmspy/plugins/__init__.py
fmspy/plugins/chat_application.py
fmspy/plugins/echo_application.py
fmspy/rtmp/__init__.py
fmspy/rtmp/assembly.py
fmspy/rtmp/constants.py
fmspy/rtmp/header.py
fmspy/rtmp/packets.py
fmspy/rtmp/status.py
fmspy/rtmp/protocol/__init__.py
fmspy/rtmp/protocol/base.py
fmspy/rtmp/protocol/client.py
fmspy/rtmp/protocol/server.py
fmspy/rtmp/tests/__init__.py
fmspy/rtmp/tests/test_assembly.py
fmspy/rtmp/tests/test_header.py
fmspy/rtmp/tests/test_packets.py
twisted/plugins/fmspy_plugin.py